zignal/__init__.py
zignal/audio.py
zignal/sndcard.py
zignal/filters/__init__.py
zignal/filters/biquads.py
zignal/filters/cic.py
zignal/filters/linearfilter.py
zignal/measure/__init__.py
zignal/measure/mls.py
zignal/measure/mlstaps.py
zignal/music/__init__.py
zignal/music/scales.py
zignal/music/spn.py
zignal-0.7.0.dist-info/METADATA
zignal-0.7.0.dist-info/WHEEL
zignal-0.7.0.dist-info/entry_points.txt
zignal-0.7.0.dist-info/licenses/LICENSE.txt
zignal-0.7.0.dist-info/RECORD
