Metadata-Version: 2.3
Name: zignal
Version: 0.7.0
Summary: Audio signal processing library
Project-URL: Homepage, https://github.com/ronnyandersson/zignal
Project-URL: Issues, https://github.com/ronnyandersson/zignal/issues
Project-URL: Download, https://pypi.python.org/pypi/zignal
Author-email: Ronny Andersson <ronny@andersson.tk>
License: MIT License
License-File: LICENSE.txt
Keywords: 12TET,CIC,DSP,FFT,FIR,IIR,audio,biquad,card,cascaded,comb,cookbook,decimation,decimator,digital,eq,equal,equaliser,equalizer,filter,filtering,finite,fourier,frequency,frequencyresponse,generator,impulse,impulseresponse,infinite,integrator,length,magnitude,magnituderesponse,maximum,maximumlengthsequence,measure,measurement,midi,mls,mlssa,notation,parametric,piano,pitch,playback,portaudio,processing,pseudo,pseudorandom,pyaudio,random,recording,response,scale,sequence,signal,signalprocess
Classifier: Development Status :: 3 - Alpha
Classifier: Environment :: Console
Classifier: Intended Audience :: Developers
Classifier: Intended Audience :: Education
Classifier: Intended Audience :: Science/Research
Classifier: License :: OSI Approved :: MIT License
Classifier: Operating System :: OS Independent
Classifier: Programming Language :: Python :: 3
Classifier: Topic :: Education
Classifier: Topic :: Multimedia :: Sound/Audio :: Analysis
Classifier: Topic :: Multimedia :: Sound/Audio :: Capture/Recording
Classifier: Topic :: Multimedia :: Sound/Audio :: Editors
Classifier: Topic :: Multimedia :: Sound/Audio :: MIDI
Classifier: Topic :: Multimedia :: Sound/Audio :: Mixers
Classifier: Topic :: Multimedia :: Sound/Audio :: Players
Classifier: Topic :: Multimedia :: Sound/Audio :: Sound Synthesis
Classifier: Topic :: Scientific/Engineering :: Mathematics
Classifier: Topic :: Software Development :: Quality Assurance
Classifier: Topic :: Software Development :: Testing
Requires-Python: >=3.8
Requires-Dist: matplotlib
Requires-Dist: numpy
Requires-Dist: scipy
Provides-Extra: dev
Requires-Dist: flake8; extra == 'dev'
Requires-Dist: isort; extra == 'dev'
Requires-Dist: pyaudio; extra == 'dev'
Provides-Extra: sndcard
Requires-Dist: pyaudio; extra == 'sndcard'
